sz_core/__init__.py
sz_core/configs/__init__.py
sz_core/configs/base.py
sz_core/encoders/__init__.py
sz_core/encoders/pydantic.py
sz_core/enums/__init__.py
sz_core/enums/base.py
sz_core/enums/env.py
sz_core/enums/errors.py
sz_core/exceptions/__init__.py
sz_core/exceptions/base.py
sz_core/ext/consul/__init__.py
sz_core/ext/consul/config.py
sz_core/ext/fastapi/__init__.py
sz_core/ext/fastapi/app.py
sz_core/ext/fastapi/handlers/__init__.py
sz_core/ext/fastapi/handlers/base.py
sz_core/ext/fastapi/handlers/base_error_handlers.py
sz_core/ext/fastapi/handlers/validation_error_handlers.py
sz_core/ext/fastapi/schemas/__init__.py
sz_core/ext/fastapi/schemas/error_wrapper.py
sz_core/ext/fastapi/schemas/response_paging.py
sz_core/ext/fastapi/schemas/response_wrapper.py
sz_core/ext/fastapi/test_utils/__init__.py
sz_core/ext/fastapi/test_utils/dependencies.py
sz_core/ext/fastapi/test_utils/http.py
sz_core/ext/graphql/__init__.py
sz_core/ext/graphql/extensions/__init__.py
sz_core/ext/graphql/extensions/auth.py
sz_core/ext/graphql/handlers.py
sz_core/ext/graphql/schema.py
sz_core/ext/graphql/typing.py
sz_core/ext/graphql/utils/pydantic_wrapper.py
sz_core/logging.py
sz_core/pydantic/__init__.py
sz_core/pydantic/base.py
sz_libs_core-0.0.0.dist-info/WHEEL
sz_libs_core-0.0.0.dist-info/METADATA
sz_libs_core-0.0.0.dist-info/RECORD
